simforge_foundry/__init__.py
simforge_foundry/py.typed
simforge_foundry/articulation/__init__.py
simforge_foundry/geometry/__init__.py
simforge_foundry/geometry/object/__init__.py
simforge_foundry/geometry/object/asteroid/__init__.py
simforge_foundry/geometry/object/asteroid/nodes.py
simforge_foundry/geometry/object/bag/__init__.py
simforge_foundry/geometry/object/bag/nodes.py
simforge_foundry/geometry/object/cubesat/__init__.py
simforge_foundry/geometry/object/cubesat/nodes.py
simforge_foundry/geometry/object/peg_in_hole/__init__.py
simforge_foundry/geometry/object/peg_in_hole/nodes_hole.py
simforge_foundry/geometry/object/peg_in_hole/nodes_module.py
simforge_foundry/geometry/object/peg_in_hole/nodes_peg.py
simforge_foundry/geometry/object/rock/__init__.py
simforge_foundry/geometry/object/rock/nodes.py
simforge_foundry/geometry/object/scoop/__init__.py
simforge_foundry/geometry/object/scoop/nodes.py
simforge_foundry/geometry/object/solar_panel/__init__.py
simforge_foundry/geometry/object/solar_panel/nodes.py
simforge_foundry/geometry/robot/__init__.py
simforge_foundry/geometry/terrain/__init__.py
simforge_foundry/geometry/terrain/mars_surface/__init__.py
simforge_foundry/geometry/terrain/mars_surface/nodes.py
simforge_foundry/geometry/terrain/moon_surface/__init__.py
simforge_foundry/geometry/terrain/moon_surface/nodes.py
simforge_foundry/image/__init__.py
simforge_foundry/material/__init__.py
simforge_foundry/material/fabric/__init__.py
simforge_foundry/material/fabric/woven_fabric/__init__.py
simforge_foundry/material/fabric/woven_fabric/nodes.py
simforge_foundry/material/metal/__init__.py
simforge_foundry/material/metal/brushed_chrome/__init__.py
simforge_foundry/material/metal/brushed_chrome/nodes.py
simforge_foundry/material/metal/scratched_metal/__init__.py
simforge_foundry/material/metal/scratched_metal/nodes.py
simforge_foundry/material/metal/smooth_gold/__init__.py
simforge_foundry/material/metal/smooth_gold/nodes.py
simforge_foundry-0.3.1.dist-info/METADATA
simforge_foundry-0.3.1.dist-info/WHEEL
simforge_foundry-0.3.1.dist-info/licenses/LICENSE-CC0
simforge_foundry-0.3.1.dist-info/RECORD
