Metadata-Version: 2.4
Name: simforge_foundry
Version: 0.3.1
Summary: Primary collection of SimForge assets
Project-URL: Repository, https://github.com/AndrejOrsula/simforge_foundry
Author-email: Andrej Orsula <orsula.andrej@gmail.com>
Maintainer-email: Andrej Orsula <orsula.andrej@gmail.com>
License: CC0-1.0
License-File: LICENSE-CC0
Keywords: procedural,simulation
Classifier: License :: CC0 1.0 Universal (CC0 1.0) Public Domain Dedication
Classifier: Programming Language :: Python
Classifier: Topic :: Games/Entertainment :: Simulation
Classifier: Topic :: Multimedia :: Graphics :: 3D Modeling
Requires-Python: >=3.11
Requires-Dist: pytest-cov>=7.0.0
Requires-Dist: simforge<1.0,>=0.1
Provides-Extra: all
Requires-Dist: pytest-env~=1.0; extra == 'all'
Requires-Dist: pytest~=8.0; extra == 'all'
Requires-Dist: simforge[bpy]; extra == 'all'
Provides-Extra: bpy
Requires-Dist: simforge[bpy]; extra == 'bpy'
Provides-Extra: test
Requires-Dist: pytest-env~=1.0; extra == 'test'
Requires-Dist: pytest~=8.0; extra == 'test'
